{
  "startTime": "2025-11-27T11:00:00Z",
  "endTime": "2025-12-04T11:00:00Z",
  "variants": [
    {
      "type": "Deep Dive",
      "name": "Sacred Cellar",
      "biome": "Fungus Bogs",
      "seed": 1759812147,
      "stages": [
        {
          "id": 1,
          "primary": "Aquarq x7",
          "secondary": "Morkite x150",
          "anomaly": null,
          "warning": "Parasites"
        },
        {
          "id": 2,
          "primary": "On-Site Refining",
          "secondary": "Black Box",
          "anomaly": "Critical Weakness",
          "warning": "Low Oxygen"
        },
        {
          "id": 3,
          "primary": "Crystal Scan x3",
          "secondary": "Morkite x150",
          "anomaly": null,
          "warning": null
        }
      ]
    },
    {
      "type": "Elite Deep Dive",
      "name": "Karl's Run",
      "biome": "Hollow Bough",
      "seed": 2403746099,
      "stages": [
        {
          "id": 1,
          "primary": "Egg x4",
          "secondary": "Mule x2",
          "anomaly": null,
          "warning": null
        },
        {
          "id": 2,
          "primary": "Aquarq x10",
          "secondary": "Morkite Well x1",
          "anomaly": null,
          "warning": "Duck and Cover"
        },
        {
          "id": 3,
          "primary": "Crystal Scan x3",
          "secondary": "Morkite Well x1",
          "anomaly": "Blood Sugar",
          "warning": "Cave Leech Cluster"
        }
      ]
    }
  ]
}