{
  "startTime": "2025-08-14T11:00:00Z",
  "endTime": "2025-08-21T11:00:00Z",
  "variants": [
    {
      "type": "Deep Dive",
      "name": "Desperate Wilderness",
      "biome": "Magma Core",
      "seed": 3380871983,
      "stages": [
        {
          "id": 1,
          "primary": "Crystal Scan x3",
          "secondary": "Mule x2",
          "anomaly": null,
          "warning": "Elite Threat"
        },
        {
          "id": 2,
          "primary": "Morkite x200",
          "secondary": "Crystal Scan x2",
          "anomaly": null,
          "warning": null
        },
        {
          "id": 3,
          "primary": "Escort Duty",
          "secondary": "Crystal Scan x2",
          "anomaly": null,
          "warning": "Duck and Cover"
        }
      ]
    },
    {
      "type": "Elite Deep Dive",
      "name": "Clean Gap",
      "biome": "Radioactive Exclusion Zone",
      "seed": 2210030218,
      "stages": [
        {
          "id": 1,
          "primary": "Morkite x250",
          "secondary": "Egg x2",
          "anomaly": null,
          "warning": "Low Oxygen"
        },
        {
          "id": 2,
          "primary": "Dreadnought x2 (H+D)",
          "secondary": "Crystal Scan x2",
          "anomaly": null,
          "warning": "Swarmageddon"
        },
        {
          "id": 3,
          "primary": "Egg x6",
          "secondary": "Black Box",
          "anomaly": "Volatile Guts",
          "warning": null
        }
      ]
    }
  ]
}